slidedown/__init__.py
slidedown/cli.py
slidedown/core.py
slidedown/file_browser.py
slidedown_cli-1.0.0.dist-info/METADATA
slidedown_cli-1.0.0.dist-info/WHEEL
slidedown_cli-1.0.0.dist-info/entry_points.txt
slidedown_cli-1.0.0.dist-info/top_level.txt
slidedown_cli-1.0.0.dist-info/RECORD
