Metadata-Version: 2.4
Name: slidedown-cli
Version: 1.0.0
Summary: A terminal-based presentation application
Author-email: mr <madushankarajapaksha999@gmail.com>
License: MIT
Project-URL: Homepage, https://github.com/MadushankaRajapaksha/slidedown
Project-URL: Repository, https://github.com/MadushankaRajapaksha/slidedown
Project-URL: Issues, https://github.com/MadushankaRajapaksha/slidedown/issues
Classifier: Development Status :: 3 - Alpha
Classifier: Intended Audience :: Developers
Classifier: License :: OSI Approved :: MIT License
Classifier: Operating System :: OS Independent
Classifier: Programming Language :: Python :: 3
Classifier: Programming Language :: Python :: 3.8
Classifier: Programming Language :: Python :: 3.9
Classifier: Programming Language :: Python :: 3.10
Classifier: Programming Language :: Python :: 3.11
Classifier: Programming Language :: Python :: 3.12
Requires-Python: >=3.8
Requires-Dist: textual>=0.41.0
